jetblack_messagebus/__init__.py
jetblack_messagebus/authentication/__init__.py
jetblack_messagebus/authentication/basic_authenticator.py
jetblack_messagebus/authentication/null_authenticator.py
jetblack_messagebus/authentication/token_authenticator.py
jetblack_messagebus/authentication/types.py
jetblack_messagebus/callback_client.py
jetblack_messagebus/client.py
jetblack_messagebus/io/__init__.py
jetblack_messagebus/io/data_packet.py
jetblack_messagebus/io/data_reader.py
jetblack_messagebus/io/data_writer.py
jetblack_messagebus/messages.py
jetblack_messagebus/utils.py
jetblack_messagebus_python3-4.1.1.dist-info/LICENSE
jetblack_messagebus_python3-4.1.1.dist-info/WHEEL
jetblack_messagebus_python3-4.1.1.dist-info/METADATA
jetblack_messagebus_python3-4.1.1.dist-info/RECORD
