Metadata-Version: 2.1
Name: jetblack-messagebus-python3
Version: 4.1.1
Summary: A python3 client for jetblack-messagebus
Home-page: https://github.com/rob-blackbourn/jetblack-messagebus-python3
License: Apache-2.0
Author: Rob Blackbourn
Author-email: rob.blackbourn@googlemail.com
Requires-Python: >=3.7,<4.0
Classifier: License :: OSI Approved :: Apache Software License
Classifier: Programming Language :: Python :: 3
Classifier: Programming Language :: Python :: 3.7
Project-URL: Repository, https://github.com/rob-blackbourn/jetblack-messagebus-python3
